heuristic_optimization/__init__.py
heuristic_optimization/base/__init__.py
heuristic_optimization/base/batch_optimizer.py
heuristic_optimization/base/iterative_optimizer.py
heuristic_optimization/base/optimizer.py
heuristic_optimization/optimizers/__init__.py
heuristic_optimization/optimizers/particle_swarm.py
heuristic_optimization/util/__init__.py
heuristic_optimization/util/position_initializers.py
heuristic_optimization/util/util.py
heuristic_optimization-0.4.3.dist-info/DESCRIPTION.rst
heuristic_optimization-0.4.3.dist-info/METADATA
heuristic_optimization-0.4.3.dist-info/RECORD
heuristic_optimization-0.4.3.dist-info/WHEEL
heuristic_optimization-0.4.3.dist-info/metadata.json
heuristic_optimization-0.4.3.dist-info/top_level.txt
