Metadata-Version: 2.0
Name: heuristic-optimization
Version: 0.4.3
Summary: Heuristics for derivative-free optimization
Home-page: https://github.com/tjanson/heuristic_optimization
Author: Tom Janson
Author-email: tom.janson@rwth-aachen.de
License: MIT
Platform: UNKNOWN
Classifier: Development Status :: 3 - Alpha
Classifier: Intended Audience :: Science/Research
Classifier: License :: OSI Approved :: MIT License
Classifier: Programming Language :: Python
Classifier: Programming Language :: Python :: 3
Classifier: Programming Language :: Python :: 3.6
Classifier: Topic :: Scientific/Engineering
Requires-Dist: numpy
